Top_3606/topsis3606.py
TOPSIS_3606-1.0.3.dist-info/LICENSE.txt
TOPSIS_3606-1.0.3.dist-info/METADATA
TOPSIS_3606-1.0.3.dist-info/WHEEL
TOPSIS_3606-1.0.3.dist-info/entry_points.txt
TOPSIS_3606-1.0.3.dist-info/top_level.txt
TOPSIS_3606-1.0.3.dist-info/RECORD
