Metadata-Version: 2.1
Name: TOPSIS-3606
Version: 1.0.3
Summary: A Python package for TOPSIS analysis of a Multiple Criteria Decision Making Problem.
Home-page: UNKNOWN
Author: Varinda Rani
Author-email: varindavg@gmail.com
License: MIT
Platform: UNKNOWN
Classifier: License :: OSI Approved :: MIT License
Classifier: Programming Language :: Python :: 3
Classifier: Programming Language :: Python :: 3.7
Requires-Dist: pandas
Requires-Dist: numpy
